.travis.yml
MANIFEST.in
README.rst
buildout.cfg
buildout_requirements.txt
setup.py
versions.cfg
collective/__init__.py
collective.recipe.zopeinstancemultiplier.egg-info/PKG-INFO
collective.recipe.zopeinstancemultiplier.egg-info/SOURCES.txt
collective.recipe.zopeinstancemultiplier.egg-info/dependency_links.txt
collective.recipe.zopeinstancemultiplier.egg-info/entry_points.txt
collective.recipe.zopeinstancemultiplier.egg-info/namespace_packages.txt
collective.recipe.zopeinstancemultiplier.egg-info/not-zip-safe
collective.recipe.zopeinstancemultiplier.egg-info/requires.txt
collective.recipe.zopeinstancemultiplier.egg-info/top_level.txt
collective/recipe/__init__.py
collective/recipe/zopeinstancemultiplier/__init__.py
collective/recipe/zopeinstancemultiplier/tests/__init__.py
collective/recipe/zopeinstancemultiplier/tests/test_docs.py
docs/HISTORY.rst