Metadata-Version: 1.1
Name: collective.recipe.zopeinstancemultiplier
Version: 0.0.1
Summary: Offers a new syntax to configure collective.recipe.supervisor
Home-page: http://pypi.python.org/pypi/collective.recipe.zopeinstancemultiplier
Author: Rafael Oliveira
Author-email: rafaelbco@gmail.com
License: GPL
Keywords: zc.buildout buildout recipe supervisor
Platform: UNKNOWN
Classifier: Framework :: Buildout :: Recipe
Classifier: Framework :: Buildout
Classifier: Intended Audience :: Developers
Classifier: Programming Language :: Python :: 2
Classifier: Programming Language :: Python :: 2.7
Classifier: Programming Language :: Python
Classifier: Topic :: Software Development :: Build Tools
